hoaipham_lib/__init__.py
hoaipham_lib/mymodule.py
hoaipham_lib-0.1.1.dist-info/LICENSE
hoaipham_lib-0.1.1.dist-info/METADATA
hoaipham_lib-0.1.1.dist-info/WHEEL
hoaipham_lib-0.1.1.dist-info/entry_points.txt
hoaipham_lib-0.1.1.dist-info/top_level.txt
hoaipham_lib-0.1.1.dist-info/RECORD
