Metadata-Version: 2.1
Name: hoaipham_lib
Version: 0.1.1
Summary: A sample Python package
Author: Hoai Pham
Author-email: hoaipham2501@gmail.com
Classifier: Programming Language :: Python :: 3
Classifier: License :: OSI Approved :: MIT License
Classifier: Operating System :: OS Independent
Requires-Python: >=3.6
License-File: LICENSE
Requires-Dist: requests==2.25.1
Requires-Dist: numpy==1.21.0
